tinkerforge_async/__init__.py
tinkerforge_async/_version.py
tinkerforge_async/async_event_bus.py
tinkerforge_async/brick_master.py
tinkerforge_async/bricklet_ambient_light_v2.py
tinkerforge_async/bricklet_ambient_light_v3.py
tinkerforge_async/bricklet_analog_in.py
tinkerforge_async/bricklet_barometer.py
tinkerforge_async/bricklet_barometer_v2.py
tinkerforge_async/bricklet_humidity.py
tinkerforge_async/bricklet_humidity_v2.py
tinkerforge_async/bricklet_industrial_dual_analog_in_v2.py
tinkerforge_async/bricklet_industrial_ptc.py
tinkerforge_async/bricklet_io16.py
tinkerforge_async/bricklet_io4_v2.py
tinkerforge_async/bricklet_isolator.py
tinkerforge_async/bricklet_moisture.py
tinkerforge_async/bricklet_motion_detector_v2.py
tinkerforge_async/bricklet_ptc.py
tinkerforge_async/bricklet_ptc_v2.py
tinkerforge_async/bricklet_rs232_v2.py
tinkerforge_async/bricklet_segment_display_4x7.py
tinkerforge_async/bricklet_segment_display_4x7_v2.py
tinkerforge_async/bricklet_temperature.py
tinkerforge_async/bricklet_temperature_v2.py
tinkerforge_async/bricklet_thermocouple_v2.py
tinkerforge_async/device_factory.py
tinkerforge_async/devices.py
tinkerforge_async/helper.py
tinkerforge_async/ip_connection.py
tinkerforge_async/ip_connection_helper.py
tinkerforge_async-1.6.2.dist-info/licenses/LICENSE
tinkerforge_async-1.6.2.dist-info/METADATA
tinkerforge_async-1.6.2.dist-info/WHEEL
tinkerforge_async-1.6.2.dist-info/top_level.txt
tinkerforge_async-1.6.2.dist-info/RECORD
