Metadata-Version: 2.4
Name: tinkerforge-async
Version: 1.6.2
Summary: Python3 AsyncIO Tinkerforge driver
Author-email: Patrick Baus <patrick.baus@physik.tu-darmstadt.de>
License-Expression: GPL-3.0-or-later
Project-URL: Homepage, https://github.com/PatrickBaus/tinkerforge_async
Project-URL: Bug Tracker, https://github.com/PatrickBaus/tinkerforge_async/issues
Project-URL: Download, https://github.com/PatrickBaus/tinkerforge_async/releases
Keywords: IoT,Tinkerforge,API
Classifier: Programming Language :: Python :: 3
Classifier: Programming Language :: Python :: 3.9
Classifier: Programming Language :: Python :: 3.10
Classifier: Programming Language :: Python :: 3.11
Classifier: Programming Language :: Python :: 3.12
Classifier: Programming Language :: Python :: 3.13
Classifier: Development Status :: 5 - Production/Stable
Classifier: Operating System :: OS Independent
Classifier: Intended Audience :: Developers
Classifier: Intended Audience :: Science/Research
Classifier: Natural Language :: English
Classifier: Topic :: Home Automation
Classifier: Topic :: Scientific/Engineering
Requires-Python: >=3.9
License-File: LICENSE
Requires-Dist: typing-extensions; python_version < "3.11"
Provides-Extra: dev
Requires-Dist: black; extra == "dev"
Requires-Dist: build; extra == "dev"
Requires-Dist: isort; extra == "dev"
Requires-Dist: mypy; extra == "dev"
Requires-Dist: pre-commit; extra == "dev"
Requires-Dist: pylint; extra == "dev"
Requires-Dist: setuptools; extra == "dev"
Requires-Dist: twine; extra == "dev"
Provides-Extra: doc
Requires-Dist: myst-parser; extra == "doc"
Requires-Dist: sphinx; extra == "doc"
Provides-Extra: test
Requires-Dist: mypy; extra == "test"
Requires-Dist: pylint; extra == "test"
Requires-Dist: pytest; extra == "test"
Requires-Dist: setuptools; extra == "test"
Dynamic: license-file
